{
    "items": [
      {"id":233705,"enchant":7628,"rune":415231},
      {"id":233620},
      {"id":233707,"enchant":2605},
      {"id":233436,"enchant":7564,"rune":440569},
      {"id":233704,"enchant":7648,"rune":408438},
      {"id":234114,"enchant":1883,"rune":432056},
      {"id":233604,"enchant":7648,"rune":408490},
      {"id":233622,"rune":415100},
      {"id":233708,"enchant":7627,"rune":408514},
      {"id":233518,"enchant":7648,"rune":408696},
      {"id":234032,"rune":442896},
      {"id":233437,"rune":442894},
      {"id":230273},
      {"id":233994},
      {"id":235009,"enchant":2568},
      {"id":231890,"enchant":7603},
      {"id":228176}
    ]
}
