{
  "items": [
    {"id":246062,"enchant":7621,"rune":429139},
    {"id":241072},
    {"id":246061,"enchant":7883,"rune":1220228},
    {"id":233519,"enchant":7667,"rune":462834},
    {"id":246060,"enchant":7645,"rune":458287},
    {"id":246056,"enchant":1883,"rune":429144},
    {"id":246055,"enchant":931,"rune":407676},
    {"id":246059,"rune":426065},
    {"id":246058,"enchant":7621,"rune":407624},
    {"id":246057,"enchant":7648,"rune":426157},
    {"id":230867,"rune":29088},
    {"id":231001,"rune":442898},
    {"id":241037},
    {"id":233994},
    {"id":236341,"enchant":2568},
    {"id":241017,"enchant":7603},
    {"id":234476}
  ]
}
