{
  "items": [
    {"id":226549,"enchant":2544,"rune":427712},
    {"id":228289},
    {"id":226550,"enchant":7325},
    {"id":227869,"enchant":2463,"rune":403511},
    {"id":226548,"enchant":1891,"rune":403668},
    {"id":226553,"enchant":1884,"rune":427717},
    {"id":226552,"rune":403501},
    {"id":226905,"rune":426316},
    {"id":226547,"enchant":2544,"rune":412689},
    {"id":226908,"enchant":911,"rune":426320},
    {"id":228287,"rune":442897},
    {"id":228687,"rune":442894},
    {"id":228255},
    {"id":223214},
    {"id":228269,"enchant":2504},
    {"id":220598},
    {"id":13396}
  ]
}
